CHANGES.rst
CONTRIBUTORS.rst
MANIFEST.in
README.rst
setup.cfg
setup.py
docs/LICENSE.GPL
docs/LICENSE.rst
docs/index.rst
src/collective/__init__.py
src/collective.ptpatcher.egg-info/PKG-INFO
src/collective.ptpatcher.egg-info/SOURCES.txt
src/collective.ptpatcher.egg-info/dependency_links.txt
src/collective.ptpatcher.egg-info/entry_points.txt
src/collective.ptpatcher.egg-info/namespace_packages.txt
src/collective.ptpatcher.egg-info/not-zip-safe
src/collective.ptpatcher.egg-info/requires.txt
src/collective.ptpatcher.egg-info/top_level.txt
src/collective/ptpatcher/__init__.py
src/collective/ptpatcher/base.py
src/collective/ptpatcher/setuphandlers.py
src/collective/ptpatcher/testing.py
src/collective/ptpatcher/tests/__init__.py
src/collective/ptpatcher/tests/configure.zcml
src/collective/ptpatcher/tests/test_patchedtemplate.py
src/collective/ptpatcher/tests/jbot/Products.CMFPlone.browser.templates.colophon.pt
src/collective/ptpatcher/tests/ptpatcher/hello_world.pt
src/collective/ptpatcher/tests/ptpatcher/plone-overview.pt
src/collective/ptpatcher/tests/robot/test_example.robot
src/collective/ptpatcher/tests/templates/hello_world.pt