Metadata-Version: 2.1
Name: collective.ptpatcher
Version: 0.0.2
Summary: Patch page templates in a sane way
Home-page: https://pypi.python.org/pypi/collective.ptpatcher
Author: Alessandro Pisa
Author-email: alessandro.pisa@gmail.com
License: GPL version 2
Keywords: Python Plone
Platform: UNKNOWN
Classifier: Environment :: Web Environment
Classifier: Framework :: Plone
Classifier: Framework :: Plone :: 5.0
Classifier: Programming Language :: Python
Classifier: Programming Language :: Python :: 2.7
Classifier: Operating System :: OS Independent
Classifier: License :: OSI Approved :: GNU General Public License v2 (GPLv2)
Provides-Extra: test
